igbot_base/__init__.py
igbot_base/additional_data.py
igbot_base/agent.py
igbot_base/agent_response.py
igbot_base/base_exception.py
igbot_base/exception_handler.py
igbot_base/llm.py
igbot_base/llmmemory.py
igbot_base/logging_adapter.py
igbot_base/models.py
igbot_base/notifier.py
igbot_base/persistable_memory.py
igbot_base/prompt_template.py
igbot_base/response_formats.py
igbot_base/retriever.py
igbot_base/tokenizer.py
igbot_base/tool.py
igbot_base/tool_merger.py
igbot_base/tool_merger_chain.py
igbot_base/tool_pre_merger.py
igbot_base/tool_pre_merger_chain.py
igbot_base/vectorstore.py
igbot_base-0.0.44.dist-info/METADATA
igbot_base-0.0.44.dist-info/WHEEL
igbot_base-0.0.44.dist-info/top_level.txt
igbot_base-0.0.44.dist-info/RECORD
