Metadata-Version: 2.4
Name: igbot_base
Version: 0.0.44
Summary: Base classes for igbot
Author-email: Igor Kopeć <igor.kopec95@gmail.com>
License: LGPL-3.0-or-later
Requires-Python: >=3.12
Requires-Dist: openai
Requires-Dist: tiktoken
